actions/__init__.py
actions/actions.py
actions_python-0.3.0.dist-info/LICENSE
actions_python-0.3.0.dist-info/METADATA
actions_python-0.3.0.dist-info/WHEEL
actions_python-0.3.0.dist-info/top_level.txt
actions_python-0.3.0.dist-info/RECORD
