Metadata-Version: 2.2
Name: actions-python
Version: 0.3.0
Summary: A simple Python packaging for managing event-like actions and validating handlers argument types.
Home-page: https://github.com/Allorak/actions-python
Author: Mike Moiseev
Author-email: mvmoiseev@miem.hse.ru
Classifier: Programming Language :: Python :: 3
Classifier: License :: OSI Approved :: MIT License
Classifier: Operating System :: OS Independent
Classifier: Development Status :: 3 - Alpha
Classifier: Natural Language :: English
Requires-Python: >=3.8
License-File: LICENSE
Dynamic: author
Dynamic: author-email
Dynamic: classifier
Dynamic: description
Dynamic: description-content-type
Dynamic: home-page
Dynamic: requires-python
Dynamic: summary
